pandaskit/__init__.py
pandaskit/_dataframe.py
pandaskit/io.py
pandaskit-0.1.0.dist-info/METADATA
pandaskit-0.1.0.dist-info/WHEEL
pandaskit-0.1.0.dist-info/RECORD
