Metadata-Version: 2.1
Name: pandaskit
Version: 0.1.0
Summary: 
Author: kyrie1218
Author-email: kyrie1218@163.com
Requires-Python: >=3.11,<4.0
Classifier: Programming Language :: Python :: 3
Classifier: Programming Language :: Python :: 3.11
Requires-Dist: ipykernel (>=6.25.1,<7.0.0)
Requires-Dist: numpy (>=1.25.2,<2.0.0)
Requires-Dist: pandas (>=2.0.3,<3.0.0)
Requires-Dist: pyreadstat (>=1.2.2,<2.0.0)
